MANTA_Ray_optics/MANTA_Ray.py
MANTA_Ray_optics/__init__.py
manta_ray_optics-1.0.2.dist-info/METADATA
manta_ray_optics-1.0.2.dist-info/WHEEL
manta_ray_optics-1.0.2.dist-info/licenses/LICENSE
manta_ray_optics-1.0.2.dist-info/RECORD
