Metadata-Version: 2.3
Name: MANTA_Ray_optics
Version: 1.0.2
Summary: MANTA-Ray (Modified Absorption of Non-spherical Tiny Aggregates in the Rayleigh regime) is a model that calculates the absorption efficiency and absorption cross-section of fractal aggregates.
Project-URL: Homepage, https://github.com/mglodge/MANTA-Ray/
Author-email: Matt Lodge <matthew.g.lodge@gmail.com>
License-File: LICENSE
Classifier: License :: OSI Approved :: MIT License
Classifier: Operating System :: OS Independent
Classifier: Programming Language :: Python :: 3
Requires-Python: >=3.0.1
